getodo/__init__.py
getodo/__main__.py
getodo/getodo.py
getodo/getodo_cfg.json
getodo/getodo_cli.py
getodo/utils.py
getodo-2.0.1.dist-info/LICENSE
getodo-2.0.1.dist-info/METADATA
getodo-2.0.1.dist-info/WHEEL
getodo-2.0.1.dist-info/entry_points.txt
getodo-2.0.1.dist-info/RECORD
