Metadata-Version: 2.1
Name: getodo
Version: 2.0.1
Summary: A python program to collect all your TODO(s)
License: MIT
Author: Vyshnav Vinod
Author-email: vyshnav.vinod003@gmail.com
Requires-Python: >=3.10,<4.0
Classifier: License :: OSI Approved :: MIT License
Classifier: Programming Language :: Python :: 3
Classifier: Programming Language :: Python :: 3.10
Classifier: Programming Language :: Python :: 3.11
Classifier: Programming Language :: Python :: 3.12
Requires-Dist: colorama (>=0.4.6,<0.5.0)
